prodot/__init__.py
prodot/_base_object.py
prodot/_dot_object.py
prodot/_path_object.py
prodot/_pro_object.py
prodot/json_tools/__init__.py
prodot/json_tools/_filter/__init__.py
prodot/json_tools/_filter/__main__.py
prodot/json_tools/_filter/_filter_byPath.py
prodot/json_tools/_filter/_filter_byValue.py
prodot/json_tools/_filter/_filtered_object.py
prodot/json_tools/_get_all_paths.py
prodot-0.3.7.dist-info/LICENSE
prodot-0.3.7.dist-info/METADATA
prodot-0.3.7.dist-info/WHEEL
prodot-0.3.7.dist-info/RECORD
