Metadata-Version: 2.1
Name: prodot
Version: 0.3.7
Summary: 
License: GNU GENERAL PUBLIC LICENSE
Author: Matheus Menezes Almeida
Author-email: mrotame@gmail.com
Requires-Python: >=3.8,<4.0
Classifier: License :: Other/Proprietary License
Classifier: Programming Language :: Python :: 3
Classifier: Programming Language :: Python :: 3.8
Classifier: Programming Language :: Python :: 3.9
Classifier: Programming Language :: Python :: 3.10
Classifier: Programming Language :: Python :: 3.11
Requires-Dist: jsonpath-ng (>=1.5.3,<2.0.0)
